cjkcms/__init__.py
cjkcms/apps.py
cjkcms/fields.py
cjkcms/forms.py
cjkcms/image_formats.py
cjkcms/search_urls.py
cjkcms/settings.py
cjkcms/urls.py
cjkcms/utils.py
cjkcms/views.py
cjkcms/wagtail_hooks.py
cjkcms/widgets.py
cjkcms/api/__init__.py
cjkcms/api/mailchimp.py
cjkcms/blocks/__init__.py
cjkcms/blocks/base_blocks.py
cjkcms/blocks/content_blocks.py
cjkcms/blocks/html_blocks.py
cjkcms/blocks/layout_blocks.py
cjkcms/blocks/searchable_html_block.py
cjkcms/draftail/__init__.py
cjkcms/draftail/draftail_extensions.py
cjkcms/draftail/draftail_icons.py
cjkcms/finders/__init__.py
cjkcms/finders/oembed.py
cjkcms/management/commands/__init__.py
cjkcms/management/commands/clear-embeds.py
cjkcms/management/commands/import-csv.py
cjkcms/management/commands/init-collections.py
cjkcms/management/commands/init-navbar.py
cjkcms/management/commands/init-website.py
cjkcms/management/commands/__pycache__/__init__.cpython-310.pyc
cjkcms/management/commands/__pycache__/clear-embeds.cpython-310.pyc
cjkcms/management/commands/__pycache__/import-csv.cpython-310.pyc
cjkcms/management/commands/__pycache__/init-collections.cpython-310.pyc
cjkcms/management/commands/__pycache__/init-navbar.cpython-310.pyc
cjkcms/management/commands/__pycache__/init-website.cpython-310.pyc
cjkcms/migrations/0001_initial.py
cjkcms/migrations/0002_alter_body_to_cjkcmsstreamfield.py
cjkcms/migrations/0003_alter_footer_content_alter_navbar_menu_items.py
cjkcms/migrations/__init__.py
cjkcms/models/__init__.py
cjkcms/models/admin_sidebar.py
cjkcms/models/cms_models.py
cjkcms/models/integration_models.py
cjkcms/models/page_models.py
cjkcms/models/snippet_models.py
cjkcms/models/wagtailsettings_models.py
cjkcms/static/cjkcms/css/cjkcms-admin.css
cjkcms/static/cjkcms/css/cjkcms-editor.css
cjkcms/static/cjkcms/css/cjkcms-front.css
cjkcms/static/cjkcms/css/cjkcms-front.css.map
cjkcms/static/cjkcms/css/cjkcms-front.min.css
cjkcms/static/cjkcms/images/avatars/default.png
cjkcms/static/cjkcms/images/avatars/default.svg
django_cjkcms-0.2.8.2.dist-info/LICENSE
django_cjkcms-0.2.8.2.dist-info/METADATA
django_cjkcms-0.2.8.2.dist-info/WHEEL
django_cjkcms-0.2.8.2.dist-info/top_level.txt
django_cjkcms-0.2.8.2.dist-info/RECORD
