Metadata-Version: 2.1
Name: django-cjkcms
Version: 0.2.8.2
Summary: Wagtail Content Management System, installable as a Django app into any Wagtail 4.x site. Based on Codered CRX.
Home-page: https://github.com/cjkpl/django-cjkcms
Author: Grzegorz Krol
Author-email: gk@cjk.pl
License: BSD-3-Clause  # Example license
Platform: UNKNOWN
Classifier: Environment :: Web Environment
Classifier: Framework :: Django
Classifier: Framework :: Django :: 4.0
Classifier: Framework :: Django :: 4.1
Classifier: Framework :: Wagtail :: 4
Classifier: Intended Audience :: Developers
Classifier: License :: OSI Approved :: BSD License
Classifier: Operating System :: OS Independent
Classifier: Programming Language :: Python
Classifier: Programming Language :: Python :: 3
Classifier: Programming Language :: Python :: 3 :: Only
Classifier: Programming Language :: Python :: 3.9
Classifier: Programming Language :: Python :: 3.10
Classifier: Topic :: Internet :: WWW/HTTP
Classifier: Topic :: Internet :: WWW/HTTP :: Site Management
Requires-Python: >=3.9
License-File: LICENSE
Requires-Dist: Wagtail (>=4.0.1)
Requires-Dist: django-bootstrap5 (>=22.1)
Requires-Dist: wagtail-cache (>=2.2.0)
Requires-Dist: wagtail-seo (>=2.3.0)
